mseq2latex/__init__.py
mseq2latex/ast_nodes.py
mseq2latex/converter.py
mseq2latex/lexer.py
mseq2latex/parser.py
mseq2latex/parsetab.py
mseq2latex-0.1.2.dist-info/METADATA
mseq2latex-0.1.2.dist-info/WHEEL
mseq2latex-0.1.2.dist-info/top_level.txt
mseq2latex-0.1.2.dist-info/RECORD
