Metadata-Version: 2.4
Name: mseq2latex
Version: 0.1.2
Summary: A simple tool to convert microsoft equation field strings to LaTeX format.
Author-email: Derican <derican112@outlook.com>, Github Copilot <copilot@github.com>
Requires-Python: >=3.10
Requires-Dist: ply>=3.11
